statworks/__init__.py
statworks-0.0.1.dist-info/LICENSE.txt
statworks-0.0.1.dist-info/METADATA
statworks-0.0.1.dist-info/RECORD
statworks-0.0.1.dist-info/WHEEL
statworks-0.0.1.dist-info/top_level.txt
tests/__init__.py
