Metadata-Version: 2.1
Name: statworks
Version: 0.0.1
Summary: Statworks is a library for professionals, who aren't statisticians, that want to use statistics in their daily work.
Home-page: https://bitbucket.org/christophevd/statworks
Author: Christophe Van Dijck
Author-email: christophe.vdijck@gmail.com
License: UNKNOWN
Platform: UNKNOWN
Classifier: Programming Language :: Python :: 3
Classifier: License :: OSI Approved :: MIT License
Classifier: Operating System :: OS Independent
